{
  "situations": [
    {
      "name": "停電查詢",
      "icon": "🔌",
      "description": "查詢停電通知、搶修進度",
      "concepts": ["停電管理", "用戶服務", "配電線路"]
    },
    {
      "name": "電表問題",
      "icon": "📊",
      "description": "電表讀數、智慧電表相關",
      "concepts": ["電表系統", "用戶服務"]
    },
    {
      "name": "用電品質",
      "icon": "⚡",
      "description": "電壓穩定、供電品質",
      "concepts": ["供電品質", "配電設備", "低壓配電"]
    },
    {
      "name": "線路維護",
      "icon": "🔧",
      "description": "配電線路、設備維護",
      "concepts": ["配電線路", "配電設備", "配電變壓器"]
    },
    {
      "name": "用戶申請",
      "icon": "📝",
      "description": "用電申請、增設服務",
      "concepts": ["用戶服務", "配電饋線", "配電變壓器"]
    },
    {
      "name": "用電資訊",
      "icon": "💡",
      "description": "用電量、電費查詢",
      "concepts": ["電表系統", "用戶服務", "低壓配電"]
    }
  ]
}
